Avivcodehackscalc/__init__.py
Avivcodehackscalc-0.1.dist-info/LICENSE.txt
Avivcodehackscalc-0.1.dist-info/METADATA
Avivcodehackscalc-0.1.dist-info/WHEEL
Avivcodehackscalc-0.1.dist-info/top_level.txt
Avivcodehackscalc-0.1.dist-info/RECORD
