Metadata-Version: 2.1
Name: Avivcodehackscalc
Version: 0.1
Summary: This is very basic calculator
Home-page: UNKNOWN
Author: Aviv Levy
Author-email: levyaviv1993@gmail.com
License: UNKNOWN
Platform: UNKNOWN
Classifier: Programming Language :: Python :: 3
Classifier: License :: OSI Approved :: MIT License
Classifier: Operating System :: OS Independent
